CHANGES.txt
LICENSE.txt
MANIFEST.in
README.txt
setup.py
RpiScratchIO/ConnectionsMgr.py
RpiScratchIO/Devices.py
RpiScratchIO/ScratchHandler.py
RpiScratchIO/ScratchIO.py
RpiScratchIO/SpiDevices.py
RpiScratchIO/__init__.py
RpiScratchIO.egg-info/PKG-INFO
RpiScratchIO.egg-info/SOURCES.txt
RpiScratchIO.egg-info/dependency_links.txt
RpiScratchIO.egg-info/requires.txt
RpiScratchIO.egg-info/top_level.txt
bin/RpiScratchIO