Metadata-Version: 1.1
Name: RpiScratchIO
Version: 0.1.6
Summary: Easy expansion of Raspberry Pi I/O within Scratch
Home-page: http://pypi.python.org/pypi/RpiScratchIO/
Author: W. H. Bell
Author-email: whbqcd1@gmail.com
License: MIT
Keywords: Raspberry Pi GPIO Scratch
Platform: UNKNOWN
Classifier: Development Status :: 3 - Alpha
Classifier: Operating System :: POSIX :: Linux
Classifier: License :: OSI Approved :: MIT License
Classifier: Intended Audience :: Developers
Classifier: Programming Language :: Python :: 2.6
Classifier: Programming Language :: Python :: 2.7
Classifier: Topic :: Software Development
Classifier: Topic :: Home Automation
Classifier: Topic :: System :: Hardware
